pyxmlfrag/__init__.py
pyxmlfrag-0.0.1.dist-info/METADATA
pyxmlfrag-0.0.1.dist-info/WHEEL
pyxmlfrag-0.0.1.dist-info/licenses/LICENSE
pyxmlfrag-0.0.1.dist-info/RECORD
