Metadata-Version: 2.1
Name: pyxmlfrag
Version: 0.0.1
Summary: Combined tree/event based XML parser
Project-URL: Homepage, https://github.com/jmtilli/pyxmlfrag
Project-URL: Issues, https://github.com/jmtilli/pyxmlfrag/issues
Author-email: Juha-Matti Tilli <juha-matti.tilli@iki.fi>
License-File: LICENSE
Classifier: License :: OSI Approved :: MIT License
Classifier: Operating System :: OS Independent
Classifier: Programming Language :: Python :: 3
Requires-Python: >=3.8
